jupyterkernelgen/__init__.py
jupyterkernelgen/__main__.py
jupyterkernelgen/jupyterkernelgen.py
jupyterkernelgen-0.1.0.dist-info/LICENSE
jupyterkernelgen-0.1.0.dist-info/METADATA
jupyterkernelgen-0.1.0.dist-info/WHEEL
jupyterkernelgen-0.1.0.dist-info/entry_points.txt
jupyterkernelgen-0.1.0.dist-info/top_level.txt
jupyterkernelgen-0.1.0.dist-info/RECORD
