Metadata-Version: 2.1
Name: jupyterkernelgen
Version: 0.1.0
Summary: A guided tool for creating jupyter kernels
Author-email: Jacob Janzen <jacob.janzen@phac-aspc.gc.ca>, Philip Mabon <philip.mabon@phac-aspc.gc.ca>
License: Apache-2.0
Project-URL: Homepage, https://github.com/phac-nml/jupyterkernelgen
Project-URL: Bug Tracker, https://github.com/phac-nml/jupyterkernelgen/issues
Classifier: Development Status :: 4 - Beta
Classifier: Environment :: Console
Classifier: Framework :: IPython
Classifier: Framework :: Jupyter
Classifier: Intended Audience :: Developers
Classifier: Intended Audience :: Science/Research
Classifier: Intended Audience :: System Administrators
Classifier: License :: OSI Approved :: Apache Software License
Classifier: Natural Language :: English
Classifier: Operating System :: POSIX :: Linux
Classifier: Programming Language :: Python :: 3.8
Requires-Python: >=3.8
License-File: LICENSE
